datasuper/__init__.py
datasuper/errors.py
datasuper/factories.py
datasuper/repo.py
datasuper/version.py
datasuper/cli/__init__.py
datasuper/cli/bio.py
datasuper/cli/cli.py
datasuper/cli/file_list.py
datasuper/database/__init__.py
datasuper/database/base_record.py
datasuper/database/constants.py
datasuper/database/database.py
datasuper/database/database_exceptions.py
datasuper/database/database_table.py
datasuper/database/file_record.py
datasuper/database/result.py
datasuper/database/sample.py
datasuper/database/sample_group.py
datasuper/database/sql_database.py
datasuper/sqldb/__init__.py
datasuper/sqldb/db.py
datasuper/sqldb/library.py
datasuper/sqldb/sample.py
datasuper/utils/__init__.py
datasuper/utils/parsers.py
datasuper/utils/savers.py
DataSuper-0.11.1.dist-info/LICENSE
DataSuper-0.11.1.dist-info/METADATA
DataSuper-0.11.1.dist-info/WHEEL
DataSuper-0.11.1.dist-info/entry_points.txt
DataSuper-0.11.1.dist-info/top_level.txt
DataSuper-0.11.1.dist-info/RECORD
